mys_goods_tool/__init__.py
mys_goods_tool/__main__.py
mys_goods_tool/api.py
mys_goods_tool/custom_css.py
mys_goods_tool/custom_widget.py
mys_goods_tool/data_model.py
mys_goods_tool/exchange_mode.py
mys_goods_tool/exchange_plan_view.py
mys_goods_tool/geetest-webui/gt3-localized.html
mys_goods_tool/geetest-webui/gt3.html
mys_goods_tool/geetest-webui/index.html
mys_goods_tool/geetest-webui/libs/gt.js
mys_goods_tool/geetest-webui/libs/gt4.js
mys_goods_tool/geetest-webui/libs/jquery.js
mys_goods_tool/geetest-webui/localized.html
mys_goods_tool/geetest.py
mys_goods_tool/login_view.py
mys_goods_tool/tui.py
mys_goods_tool/user_data.py
mys_goods_tool/utils.py
mys_goods_tool-2.1.0.dist-info/LICENSE
mys_goods_tool-2.1.0.dist-info/METADATA
mys_goods_tool-2.1.0.dist-info/WHEEL
mys_goods_tool-2.1.0.dist-info/RECORD
