Metadata-Version: 2.1
Name: mys-goods-tool
Version: 2.1.0
Summary: 米游社商品兑换工具|短信验证登录|终端TUI界面
Home-page: https://github.com/Ljzd-PRO/Mys_Goods_Tool
Keywords: mihoyo,mihoyobbs,genshin impact,textual,tui
Author: Ljzd-PRO
Author-email: ljzd@office.ljzd-pro.ml
Requires-Python: >=3.9,<3.12
Classifier: Development Status :: 5 - Production/Stable
Classifier: License :: OSI Approved :: MIT License
Classifier: Operating System :: OS Independent
Classifier: Programming Language :: Python :: 3
Classifier: Programming Language :: Python :: 3.9
Classifier: Programming Language :: Python :: 3.10
Classifier: Programming Language :: Python :: 3.11
Requires-Dist: apscheduler (>=3.10.1,<4.0.0)
Requires-Dist: httpx (>=0.24.1,<0.25.0)
Requires-Dist: loguru (>=0.7.0,<0.8.0)
Requires-Dist: ntplib (>=0.4.0,<0.5.0)
Requires-Dist: ping3 (>=4.0.4,<5.0.0)
Requires-Dist: pydantic (>=1.10.9,<2.0.0)
Requires-Dist: requests (>=2.31.0,<3.0.0)
Requires-Dist: rich (>=13.4.2,<14.0.0)
Requires-Dist: socksio (>=1.0.0,<2.0.0)
Requires-Dist: tenacity (>=8.2.2,<9.0.0)
Requires-Dist: textual (>=0.27.0,<0.28.0)
Project-URL: Bug Tracker, https://github.com/Ljzd-PRO/Mys_Goods_Tool/issues
Project-URL: Documentation, https://github.com/Ljzd-PRO/Mys_Goods_Tool/wiki
Project-URL: Repository, https://github.com/Ljzd-PRO/Mys_Goods_Tool
